addressparser/__init__.py
addressparser/__main__.py
addressparser/drawer.py
addressparser/exceptions.py
addressparser/pca.csv
addressparser/structures.py
addressparser_x-0.0.3.dist-info/LICENSE
addressparser_x-0.0.3.dist-info/METADATA
addressparser_x-0.0.3.dist-info/WHEEL
addressparser_x-0.0.3.dist-info/entry_points.txt
addressparser_x-0.0.3.dist-info/RECORD
