Metadata-Version: 2.1
Name: addressparser-x
Version: 0.0.3
Summary: Chinese Address Parser and Extraction Tool,Chinese Province, City and Area Recognition Utilities
License: MIT
Author: xxxxxxxxxxxx
Requires-Python: >=2.7
Classifier: License :: OSI Approved :: MIT License
Classifier: Programming Language :: Python :: 2
Classifier: Programming Language :: Python :: 2.7
Classifier: Programming Language :: Python :: 3
Classifier: Programming Language :: Python :: 3.4
Classifier: Programming Language :: Python :: 3.5
Classifier: Programming Language :: Python :: 3.6
Classifier: Programming Language :: Python :: 3.7
Classifier: Programming Language :: Python :: 3.8
Classifier: Programming Language :: Python :: 3.9
Classifier: Programming Language :: Python :: 3.10
Classifier: Programming Language :: Python :: 3.11
Requires-Dist: jieba (>=0.42.1,<0.43.0)
Requires-Dist: pandas (>=1.3.0,<2.0.0)
